psrecord/__init__.py
psrecord/__main__.py
psrecord/_version.py
psrecord/main.py
psrecord/tests/__init__.py
psrecord/tests/test_main.py
psrecord_io-1.5.0.dist-info/licenses/LICENSE
psrecord_io-1.5.0.dist-info/METADATA
psrecord_io-1.5.0.dist-info/WHEEL
psrecord_io-1.5.0.dist-info/entry_points.txt
psrecord_io-1.5.0.dist-info/top_level.txt
psrecord_io-1.5.0.dist-info/zip-safe
psrecord_io-1.5.0.dist-info/RECORD
