Metadata-Version: 2.4
Name: psrecord-io
Version: 1.5.0
Summary: Python package to record activity from processes
Author-email: Thomas Robitaille <thomas.robitaille@gmail.com>, Rui Xue <rx.astro@gmail.com>
Maintainer-email: Rui Xue <rx.astro@gmail.com>
License: Simplified BSD License
Project-URL: Repository, https://github.com/r-xue/psrecord
Project-URL: Original Project, https://github.com/astrofrog/psrecord
Keywords: psrecord,fork,io,data-processing
Classifier: Development Status :: 4 - Beta
Classifier: Programming Language :: Python :: 3
Classifier: Intended Audience :: Developers
Classifier: License :: OSI Approved :: BSD License
Provides: psrecord
License-File: LICENSE
Requires-Dist: psutil>=5.6
Provides-Extra: test
Requires-Dist: pytest>=7.0; extra == "test"
Provides-Extra: plot
Requires-Dist: matplotlib; extra == "plot"
Dynamic: license-file
